sima_torch/__init__.py
sima_torch/keyboard_policy.py
sima_torch/phenaki_wrapper.py
sima_torch/transformer.py
sima_torch-0.0.2.dist-info/LICENSE
sima_torch-0.0.2.dist-info/METADATA
sima_torch-0.0.2.dist-info/WHEEL
sima_torch-0.0.2.dist-info/RECORD
